{"learn_about.md":"f2890f6e","readme.md":"4aa04c7a","guides_use-tia-for-gas.md":"77a614ce","learn_building-and-deploying-a-rollup.md":"cf429071","index.md":"533269a3","tutorials_gm-world.md":"036d78d0","guides_max-pending-blocks.md":"ccfe3cce","guides_overview.md":"5218cee3","tutorials_quick-start.md":"28628520","guides_create-genesis.md":"73af8a83","testnets_cosmwasm-testnet.md":"8a3bfdf0","tutorials_cosmwasm.md":"2c342b30","guides_ibc-connection.md":"928cb3c7","tutorials_celestia-da.md":"c32ccd34","guides_connect-local-da.md":"cd88ebfa","tutorials_gm-world-arabica-testnet.md":"fc49c8f6","guides_restart-rollup.md":"212b5331","tutorials_wordle.md":"a842ed76","guides_block-times.md":"d58d05f2","guides_da-block-time.md":"b4359b35","tutorials_gm-world-mainnet.md":"61cdeed5","blog_overview.md":"23ffbe71","tutorials_gm-world-frontend.md":"69afb3ad","blog_rollkit-the-first-sovereign-rollup-framework.md":"34c4ad31","guides_cw-orch.md":"c9cfb537","guides_lazy-sequencing.md":"ebb9090a","guides_gas-price.md":"31c418dd","learn_stack.md":"187ebd21","learn_intro.md":"eb285fb8","learn_specifications.md":"efcf9e58","guides_zkml.md":"c6bc2111","tutorials_polaris-evm.md":"c18ed3b7","learn_transaction-flow.md":"07951f77","tutorials_gm-world-mocha-testnet.md":"5b612bff","guides_full-and-sequencer-node.md":"d40b01e6","guides_rollkit-monitoring.md":"a4569e72","blog_sovereign-rollups-on-bitcoin.md":"dc2dc4bc","tutorials_bitcoin.md":"68cdd239"}
