{"blog_overview.md":"y1XlBO1U","blog_rollkit-the-first-sovereign-rollup-framework.md":"BRrQCn2o","blog_sovereign-rollups-on-bitcoin.md":"DVzyOqWw","guides_cometbft-to-rollkit.md":"BjlAOwnr","guides_config.md":"BMt5ksJa","guides_create-genesis.md":"BS2PZs31","guides_cw-orch.md":"BNzNPo8R","guides_evm-based.md":"r8lAd3_P","guides_evm-single-guide.md":"CSxvOa-e","guides_gas-price.md":"P1D3_OAK","guides_ibc-connection.md":"BvyyE9EC","guides_ignite-rollkit.md":"BtQ_0yFE","guides_metrics.md":"5nNWRWqr","guides_overview.md":"2jZkTGSs","guides_reset-state.md":"DQmI2HEC","guides_restart-rollup.md":"B4RkCuqr","guides_use-tia-for-gas.md":"EgxTpB4V","guides_zkml.md":"BV-AMyme","index.md":"DZiHtHLV","learn_about.md":"BtkWwn9m","learn_building-and-deploying-a-rollup.md":"MCVMm1GW","learn_intro.md":"B_QkKAJq","learn_specifications.md":"DwB6JCdV","learn_stack.md":"BcAegABP","learn_transaction-flow.md":"B32hr-iR","readme.md":"CXp__09L","testnets_cosmwasm-testnet.md":"BYS1pWtM","tutorials_bitcoin.md":"Cq7WqXyP","tutorials_da_celestia-da.md":"ClZQ94Je","tutorials_da_local-da.md":"BX1W1ybl","tutorials_da_overview.md":"C3XwP3Xk","tutorials_deploy-overview.md":"CEDCoTep","tutorials_docker-compose.md":"lX28NTRY","tutorials_execution_cosmwasm.md":"PGDFd4w5","tutorials_gm-world.md":"C_B7SS9d","tutorials_quick-start.md":"CKbHL4X3","tutorials_sequencing_based.md":"BT-5EW4P","tutorials_sequencing_forced-inclusion.md":"DjaiJuPH","tutorials_sequencing_overview.md":"CMLCJlf7","tutorials_wordle.md":"BQg3sRle"}
