{"blog_overview.md":"FRnBuKtJ","blog_rollkit-the-first-sovereign-rollup-framework.md":"BRcL7_Gz","blog_sovereign-rollups-on-bitcoin.md":"CFcKLa13","guides_block-times.md":"BJnLWqEn","guides_cometbft-to-rollkit.md":"DWBz6j--","guides_connect-local-da.md":"DSehch8i","guides_create-genesis.md":"aSAdJ25y","guides_cw-orch.md":"D51tWbQn","guides_da-block-time.md":"DuaKw3u1","guides_full-node.md":"QyfUB0d0","guides_gas-price.md":"wjptAakf","guides_ibc-connection.md":"BPGm5Zdh","guides_ignite-rollkit.md":"B6T2iO5r","guides_lazy-sequencing.md":"Tu6eOFqY","guides_max-pending-blocks.md":"DbDswzhk","guides_overview.md":"C09hiifS","guides_restart-rollup.md":"DaVZ7C27","guides_rollkit-monitoring.md":"CpIYSNI2","guides_use-rollkit-cli.md":"Cc4Yzvup","guides_use-tia-for-gas.md":"DxjvX8ps","guides_zkml.md":"B7BXRRop","index.md":"BuKOoI-X","learn_about.md":"DYRaQo4W","learn_building-and-deploying-a-rollup.md":"CrUaaT13","learn_intro.md":"TCqNWDNC","learn_specifications.md":"CDArJZJk","learn_stack.md":"BGd7TTMP","learn_transaction-flow.md":"CACtXhEl","readme.md":"CLDDODmy","testnets_cosmwasm-testnet.md":"BeDmzJyK","tutorials_artela-evm-plus-plus.md":"BExi-rqu","tutorials_avail-da.md":"vlenUdvt","tutorials_beaconkit.md":"CzPyr2w2","tutorials_bitcoin.md":"OxilvgeP","tutorials_celestia-da.md":"CVS1jYfk","tutorials_cosmwasm.md":"BE7JnYoO","tutorials_evm-contract-interaction.md":"Ca7FlDQG","tutorials_gm-world.md":"DwllE3Iq","tutorials_octane-evm.md":"Bg6VnbFv","tutorials_polaris-evm.md":"tQolID0N","tutorials_quick-start.md":"BmNL715W","tutorials_wordle.md":"DEG0CI_Y"}
