{"learn_stack.md":"ac4b66e1","tutorials_cw-orch.md":"60154752","learn_basic-rollup.md":"c7c09f5b","blog_overview.md":"8c5d5b59","tutorials_lazy-sequencing.md":"f0e9ca4e","learn_overview.md":"250dc04a","learn_intro.md":"8ea99e54","tutorials_overview.md":"5952cae2","learn_pessimistic-rollup-with-a-shared-sequencer.md":"dadc723a","tutorials_gm-world-arabica-testnet.md":"a2d553e0","readme.md":"5a24b6f8","tutorials_zkml.md":"f990ef9b","tutorials_gm-world.md":"52c9e030","tutorials_wordle.md":"b93bc47b","tutorials_gm-world-frontend.md":"9afd08da","tutorials_recipe-book.md":"6e06b497","tutorials_rollup-docker.md":"9d6a2f32","learn_transaction-flow.md":"8ea9169f","tutorials_gm-world-mocha-testnet.md":"5fd246d4","tutorials_gm-world-mainnet.md":"a7e450b3","learn_readme.md":"b5950b4d","learn_building-and-deploying-a-rollup.md":"0aa4ebbe","tutorials_restart-rollup.md":"6fc878f8","tutorials_cosmwasm.md":"a828b125","tutorials_starter-rollup.md":"934a6a99","index.md":"4921acea","tutorials_ibc-connection.md":"7f362306","learn_rollup-glossary.md":"06dde7e3","tutorials_gas-price.md":"f19a3022","tutorials_block-times.md":"c3546632","learn_based-pessimistic-rollup.md":"a0b943e3","tutorials_full-and-sequencer-node.md":"18605cb0","tutorials_bitcoin.md":"b26dfe4e","learn_about.md":"20580974","tutorials_polaris-evm.md":"b19f5e44"}
