{"tutorials_celestia-da.md":"2eb34924","guides_restart-rollup.md":"d8671da7","guides_block-times.md":"08f3a270","tutorials_polaris-evm.md":"e3206717","blog_overview.md":"19b82987","guides_zkml.md":"3b0a50f8","tutorials_gm-world-mainnet.md":"064c42a7","learn_stack.md":"af081c10","tutorials_gm-world-mocha-testnet.md":"86c45f38","tutorials_gm-world.md":"8c5481a8","tutorials_quick-start.md":"7048a485","guides_ibc-connection.md":"35ff6e26","tutorials_gm-world-frontend.md":"d7175cd3","tutorials_wordle.md":"33a2049e","blog_rollkit-the-first-sovereign-rollup-framework.md":"04a9f8ec","learn_building-and-deploying-a-rollup.md":"36427dfa","learn_intro.md":"6bfa2429","tutorials_bitcoin.md":"a0dc88fe","guides_lazy-sequencing.md":"4648be1f","guides_overview.md":"7218c8a9","index.md":"8f11e78e","learn_transaction-flow.md":"4b858595","guides_cw-orch.md":"52455287","readme.md":"1933cdd3","learn_about.md":"8f2000ec","blog_sovereign-rollups-on-bitcoin.md":"5162af08","guides_full-and-sequencer-node.md":"20d1e5cd","tutorials_gm-world-arabica-testnet.md":"3ee9aaac","guides_gas-price.md":"fa020c20","tutorials_cosmwasm.md":"2f287bdc","guides_rollkit-monitoring.md":"8de7d48f","testnets_cosmwasm-testnet.md":"7b61fd72"}
