{"blog_overview.md":"D4_RVCH9","blog_rollkit-the-first-sovereign-rollup-framework.md":"BXTAk6R4","blog_sovereign-rollups-on-bitcoin.md":"C8A5cccd","guides_block-times.md":"CJq_qjQn","guides_cometbft-to-rollkit.md":"q32lnREX","guides_create-genesis.md":"Dnsnx4uc","guides_cw-orch.md":"BuiWW1C9","guides_da-block-time.md":"DMKNvPvT","guides_full-node.md":"ujOkWLku","guides_gas-price.md":"BVlNl3YB","guides_ibc-connection.md":"D05odX5d","guides_ignite-rollkit.md":"veM54Sor","guides_lazy-sequencing.md":"D0wvUopS","guides_max-pending-blocks.md":"Fut-VsZz","guides_overview.md":"CQdK2qDv","guides_restart-rollup.md":"CEETMLBQ","guides_rollkit-monitoring.md":"xeaAjkRq","guides_use-rollkit-cli.md":"C3F1Ylxu","guides_use-tia-for-gas.md":"CEv_qgMb","guides_zkml.md":"B2GW0i4E","index.md":"Dv-uBuOO","learn_about.md":"Ch12RGcK","learn_building-and-deploying-a-rollup.md":"B1Znay0m","learn_intro.md":"C_TY8xp6","learn_specifications.md":"CovSY0qL","learn_stack.md":"DWiR6JVg","learn_transaction-flow.md":"ByNf05of","readme.md":"BPWwD1r1","testnets_cosmwasm-testnet.md":"BFkw4N_1","tutorials_artela-evm-plus-plus.md":"CCKX-6PN","tutorials_beaconkit.md":"Ds51da-N","tutorials_bitcoin.md":"CnKC2K_g","tutorials_cosmwasm.md":"C_4tys6X","tutorials_da_avail-da.md":"CvM_9_MH","tutorials_da_celestia-da.md":"C5pgjl62","tutorials_da_local-da.md":"CFJydOm0","tutorials_da_overview.md":"D04wHHic","tutorials_deploy-overview.md":"BwSJEH4U","tutorials_docker-compose.md":"x_SMeXP_","tutorials_evm-contract-interaction.md":"DardMAmR","tutorials_gm-world.md":"DPiC5bzO","tutorials_kurtosis.md":"PTQ7_y8S","tutorials_octane-evm.md":"DWEJSDjw","tutorials_polaris-evm.md":"CKlUtpym","tutorials_quick-start.md":"CwbEKhXf","tutorials_sequencing_astria.md":"BQBRnxyR","tutorials_sequencing_based.md":"Crl2Mk4c","tutorials_sequencing_centralized.md":"BN_Ndx2O","tutorials_sequencing_forced-inclusion.md":"CxbttaB_","tutorials_sequencing_local.md":"BILxdZ0D","tutorials_sequencing_overview.md":"C_qlYgHZ","tutorials_wordle.md":"C-XkBTst"}
