{"guides_connect-local-da.md":"d8c1d199","readme.md":"078faf7e","guides_block-times.md":"2a64d90e","blog_rollkit-the-first-sovereign-rollup-framework.md":"1104d751","learn_specifications.md":"35fe7123","blog_sovereign-rollups-on-bitcoin.md":"c85ca1e7","guides_create-genesis.md":"a574f045","tutorials_quick-start.md":"cefcb5d4","guides_max-pending-blocks.md":"21d03ae6","tutorials_gm-world.md":"139e28a0","tutorials_bitcoin.md":"f4a2f24c","tutorials_celestia-da.md":"da726f98","tutorials_cosmwasm.md":"d81e689b","guides_da-block-time.md":"9058511e","tutorials_gm-world-mainnet.md":"f9d11d35","tutorials_gm-world-mocha-testnet.md":"031247d2","guides_full-and-sequencer-node.md":"fc584483","index.md":"52290c44","guides_rollkit-monitoring.md":"a1732483","tutorials_wordle.md":"115acc8a","guides_zkml.md":"d76b7df6","learn_transaction-flow.md":"b1422b07","blog_overview.md":"7375a256","tutorials_gm-world-arabica-testnet.md":"9bf976dc","guides_lazy-sequencing.md":"db4fd07d","guides_use-rollkit-cli.md":"262d2cd7","tutorials_avail-da.md":"cffb48e4","learn_intro.md":"b2ed19b3","guides_overview.md":"1e01292f","tutorials_polaris-evm.md":"b7dd96d9","learn_stack.md":"950f50d2","learn_building-and-deploying-a-rollup.md":"57e01974","testnets_cosmwasm-testnet.md":"a3ce6993","guides_ibc-connection.md":"a86c12c8","guides_cw-orch.md":"404059fe","guides_use-tia-for-gas.md":"7787d2bf","guides_gas-price.md":"bf5eaa36","learn_about.md":"0495a695","guides_restart-rollup.md":"16287799","tutorials_gm-world-frontend.md":"62b6b142"}
