{"blog_overview.md":"BsiEQKg3","blog_rollkit-the-first-sovereign-rollup-framework.md":"Dp2uNtnI","guides_cometbft-to-rollkit.md":"CPZfmgOy","guides_create-genesis.md":"BDSzhwZ1","guides_da_celestia-da.md":"D8IVc0qN","guides_da_local-da.md":"DQ_RzQ_n","guides_deploy-overview.md":"DFmSI8pH","guides_docker-compose.md":"BtMbIaZE","guides_evm_reth-backup.md":"wbTMXwu5","guides_evm_single.md":"BK3INscm","guides_execution_cosmwasm.md":"CIBnAPEW","guides_full-node.md":"B3rkY47J","guides_gm-world.md":"BMgA0HKc","guides_metrics.md":"ZuuV8Je8","guides_quick-start.md":"DkOPcnlG","guides_reset-state.md":"CTmaEwJw","guides_restart-rollup.md":"B6aC9ZgG","guides_use-tia-for-gas.md":"CnICRu5r","index.md":"B59xYK6B","learn_about.md":"COdozuXN","learn_config.md":"DFveCHZ5","learn_data-availability.md":"tm8LOH2w","learn_execution.md":"B0auReIg","learn_sequencing_overview.md":"D02ji1ym","learn_sequencing_single.md":"CKT4vjMh","learn_specifications.md":"BWZhqu2t","learn_transaction-flow.md":"CNukMU1F","readme.md":"C_JdDE4K"}
