{"blog_overview.md":"465f79f5","tutorials_celestia-da.md":"d58fa86e","blog_sovereign-rollups-on-bitcoin.md":"e756ac2e","guides_create-genesis.md":"198fe92f","learn_stack.md":"32002009","learn_transaction-flow.md":"03ae153c","testnets_cosmwasm-testnet.md":"f8375818","tutorials_artela-evm-plus-plus.md":"7c062ba4","tutorials_octane-evm.md":"ed85ea5a","blog_rollkit-the-first-sovereign-rollup-framework.md":"91b0fb28","tutorials_quick-start.md":"db147937","guides_cw-orch.md":"e2d7c994","tutorials_gm-world-mainnet.md":"8627251c","learn_intro.md":"e7ba5958","tutorials_gm-world-mocha-testnet.md":"be2a8b36","guides_block-times.md":"c192e730","tutorials_polaris-evm.md":"0bdd85a6","guides_gas-price.md":"460e10be","guides_use-rollkit-cli.md":"997080cd","guides_use-tia-for-gas.md":"271b6442","readme.md":"149e71ec","guides_connect-local-da.md":"c70d1763","tutorials_evm-contract-interaction.md":"dc74013a","guides_ibc-connection.md":"c8646db7","index.md":"bbd6e347","guides_zkml.md":"d26f564b","guides_max-pending-blocks.md":"23a59db0","learn_building-and-deploying-a-rollup.md":"58154f1d","learn_about.md":"ac9eb922","tutorials_gm-world-arabica-testnet.md":"0366a7a3","guides_restart-rollup.md":"a1dfda83","tutorials_wordle.md":"4c79a7f7","tutorials_avail-da.md":"5b392fee","guides_da-block-time.md":"3866e1c4","guides_lazy-sequencing.md":"595f5e67","guides_full-and-sequencer-node.md":"25a18b1c","tutorials_cosmwasm.md":"a63a2d5e","guides_rollkit-monitoring.md":"131b3e77","tutorials_bitcoin.md":"fa534b98","guides_overview.md":"ef5dec0c","tutorials_gm-world.md":"60c4a648","learn_specifications.md":"3165c448","tutorials_beaconkit.md":"2476af7b"}
