{"readme.md":"df4bf86b","guides_connect-local-da.md":"7e0105dd","guides_block-times.md":"51350aba","blog_overview.md":"9002dce4","tutorials_quick-start.md":"3d8dc776","tutorials_gm-world-mainnet.md":"2f7aa921","tutorials_gm-world-arabica-testnet.md":"38f2a4a9","guides_restart-rollup.md":"11de57d5","guides_lazy-sequencing.md":"8829d432","guides_full-and-sequencer-node.md":"147e9a81","blog_sovereign-rollups-on-bitcoin.md":"1ca1640e","guides_use-tia-for-gas.md":"5b23d0be","testnets_cosmwasm-testnet.md":"10882ac8","tutorials_gm-world-mocha-testnet.md":"4997a47a","guides_zkml.md":"ac9e022c","index.md":"851cbc16","guides_use-rollkit-cli.md":"d341e7e5","tutorials_gm-world.md":"0fe44d04","blog_rollkit-the-first-sovereign-rollup-framework.md":"4d349fae","guides_max-pending-blocks.md":"c8ab378a","tutorials_polaris-evm.md":"68f95886","tutorials_wordle.md":"4391e97c","tutorials_bitcoin.md":"4bd8c5a6","learn_about.md":"e0df595f","guides_rollkit-monitoring.md":"35ab3716","guides_create-genesis.md":"e54e0a91","learn_building-and-deploying-a-rollup.md":"a062b248","learn_stack.md":"f25c4451","guides_cw-orch.md":"4c83781f","tutorials_beaconkit.md":"5b69d880","tutorials_celestia-da.md":"dc0903b9","guides_da-block-time.md":"ff25a6c1","guides_ibc-connection.md":"160ab85b","learn_specifications.md":"a4b3bee8","guides_overview.md":"8f4047bf","tutorials_evm-contract-interaction.md":"71c986c3","tutorials_cosmwasm.md":"260ec8d9","tutorials_octane-evm.md":"66dd98bc","learn_intro.md":"008c3b5b","tutorials_avail-da.md":"5f4a66e3","guides_gas-price.md":"b20d1e02","learn_transaction-flow.md":"f06331f7"}
